certora_bins/__init__.py
certora_cli/__init__.py
certora_cli/certoraEVMProver.py
certora_cli/certoraEqCheck.py
certora_cli/certoraMutate.py
certora_cli/certoraRun.py
certora_cli/certoraSolanaProver.py
certora_cli/certoraSorobanProver.py
certora_cli/rustMutator.py
certora_cli/CertoraProver/__init__.py
certora_cli/CertoraProver/certoraBuild.py
certora_cli/CertoraProver/certoraBuildCacheManager.py
certora_cli/CertoraProver/certoraBuildDataClasses.py
certora_cli/CertoraProver/certoraBuildRust.py
certora_cli/CertoraProver/certoraCloudIO.py
certora_cli/CertoraProver/certoraCollectConfigurationLayout.py
certora_cli/CertoraProver/certoraCollectRunMetadata.py
certora_cli/CertoraProver/certoraCompilerParameters.py
certora_cli/CertoraProver/certoraConfigIO.py
certora_cli/CertoraProver/certoraContext.py
certora_cli/CertoraProver/certoraContextAttributes.py
certora_cli/CertoraProver/certoraContextClass.py
certora_cli/CertoraProver/certoraContextValidator.py
certora_cli/CertoraProver/certoraContractFuncs.py
certora_cli/CertoraProver/certoraExtensionInfo.py
certora_cli/CertoraProver/certoraJobList.py
certora_cli/CertoraProver/certoraMiniSpecParser.py
certora_cli/CertoraProver/certoraNodeFilters.py
certora_cli/CertoraProver/certoraParseBuildScript.py
certora_cli/CertoraProver/certoraProjectScanner.py
certora_cli/CertoraProver/certoraSourceFinders.py
certora_cli/CertoraProver/certoraType.py
certora_cli/CertoraProver/certoraVerifyGenerator.py
certora_cli/CertoraProver/splitRules.py
certora_cli/CertoraProver/Compiler/CompilerCollector.py
certora_cli/CertoraProver/Compiler/CompilerCollectorFactory.py
certora_cli/CertoraProver/Compiler/CompilerCollectorSol.py
certora_cli/CertoraProver/Compiler/CompilerCollectorSolBased.py
certora_cli/CertoraProver/Compiler/CompilerCollectorVy.py
certora_cli/CertoraProver/Compiler/CompilerCollectorYul.py
certora_cli/CertoraProver/Compiler/__init__.py
certora_cli/EquivalenceCheck/Eq_default.conf
certora_cli/EquivalenceCheck/Eq_mc_no_out_template.spec
certora_cli_alpha_oz_beta-20250403.10.28.262732.dist-info/LICENSE
certora_cli_alpha_oz_beta-20250403.10.28.262732.dist-info/METADATA
certora_cli_alpha_oz_beta-20250403.10.28.262732.dist-info/WHEEL
certora_cli_alpha_oz_beta-20250403.10.28.262732.dist-info/entry_points.txt
certora_cli_alpha_oz_beta-20250403.10.28.262732.dist-info/top_level.txt
certora_cli_alpha_oz_beta-20250403.10.28.262732.dist-info/RECORD
