Metadata-Version: 2.2
Name: certora-cli-alpha-oz-beta
Version: 20250403.10.28.262732
Summary: Runner for the Certora Prover
Home-page: https://pypi.org/project/certora-cli-alpha-oz-beta
Author: Certora
Author-email: support@certora.com
Classifier: Programming Language :: Python :: 3
Classifier: License :: OSI Approved :: MIT License
Classifier: Operating System :: OS Independent
Requires-Python: >=3.8
License-File: LICENSE
Requires-Dist: click
Requires-Dist: json5
Requires-Dist: pycryptodome
Requires-Dist: requests
Requires-Dist: rich
Requires-Dist: sly
Requires-Dist: tabulate
Requires-Dist: tqdm
Requires-Dist: StrEnum
Requires-Dist: universalmutator
Requires-Dist: jinja2
Dynamic: author
Dynamic: author-email
Dynamic: classifier
Dynamic: description
Dynamic: description-content-type
Dynamic: home-page
Dynamic: requires-dist
Dynamic: requires-python
Dynamic: summary
